airbornerf/Client.py
airbornerf/Tile.py
airbornerf/__init__.py
airbornerf/jsog.py
airbornerf_sdk-1.4.8.dist-info/METADATA
airbornerf_sdk-1.4.8.dist-info/WHEEL
airbornerf_sdk-1.4.8.dist-info/top_level.txt
airbornerf_sdk-1.4.8.dist-info/RECORD
