Metadata-Version: 2.1
Name: airbornerf-sdk
Version: 1.4.8
Summary: AirborneRF SDK
Home-page: https://www.airbornerf.com/
Author: Thomas Wana
Author-email: support@airbornerf.com
License: Proprietary
Platform: UNKNOWN
Requires-Dist: requests
